[
  {
    "uuid": "689bb394-c159-4d90-88de-40c847736593",
    "name": "glsaenz",
    "level": 4,
    "bypassesPlayerLimit": false
  },
  {
    "uuid": "a8487536-68b1-4763-92a1-3666da68f9c6",
    "name": "esaenz28",
    "level": 4,
    "bypassesPlayerLimit": false
  },
  {
    "uuid": "6355c36c-b05b-41f3-867a-14a0113b947e",
    "name": "jpcrat",
    "level": 4,
    "bypassesPlayerLimit": false
  },
  {
    "uuid": "56cd5107-4334-4af2-9aa3-9f3dc8795444",
    "name": "Emily_Alice",
    "level": 4,
    "bypassesPlayerLimit": false
  }
]